awscli_plugin_logs_tail/__init__.py
awscli_plugin_logs_tail/tail.py
awscli_plugin_logs_tail-0.2.dist-info/LICENSE
awscli_plugin_logs_tail-0.2.dist-info/METADATA
awscli_plugin_logs_tail-0.2.dist-info/WHEEL
awscli_plugin_logs_tail-0.2.dist-info/top_level.txt
awscli_plugin_logs_tail-0.2.dist-info/RECORD
