Metadata-Version: 2.1
Name: awscli-plugin-logs-tail
Version: 0.2
Summary: CloudWatch Logs tail command plugin for AWS CLI
Home-page: https://github.com/corymbia/logs-tail-awscli-plugin
Author: Steve Jones
Author-email: steve@iaascream.cloud
License: BSD (Simplified)
Keywords: awscli,cloudwatch
Platform: UNKNOWN
Classifier: Development Status :: 4 - Beta
Classifier: License :: OSI Approved :: BSD License
Classifier: Operating System :: OS Independent
Classifier: Programming Language :: Python
Classifier: Programming Language :: Python :: 2
Classifier: Programming Language :: Python :: 2.7
Classifier: Topic :: Internet
Requires-Dist: awscli (>=1.14.0)
Requires-Dist: botocore (>=1.8.35)
Requires-Dist: colorama (>=0.3.2)
Requires-Dist: python-dateutil (>=1.4)
